Topsis/__init__.py
Topsis/topsis.py
topsis_sushant_jindal_102303048-0.2.dist-info/licenses/LICENSE.txt
topsis_sushant_jindal_102303048-0.2.dist-info/METADATA
topsis_sushant_jindal_102303048-0.2.dist-info/WHEEL
topsis_sushant_jindal_102303048-0.2.dist-info/top_level.txt
topsis_sushant_jindal_102303048-0.2.dist-info/RECORD
