Metadata-Version: 2.4
Name: Topsis_Sushant_Jindal_102303048
Version: 0.2
Summary: A Topsis Report Generator
Author: Sushant Jindal
Author-email: sjindal4_be23@thapar.edu
Classifier: Programming Language :: Python :: 3
Classifier: License :: OSI Approved :: MIT License
Classifier: Operating System :: OS Independent
License-File: LICENSE.txt
Dynamic: author
Dynamic: author-email
Dynamic: classifier
Dynamic: license-file
Dynamic: summary
